{
  "hymnNumber": 435,
  "title": "Praise",
  "author": {
    "name": "",
    "birthYear": "",
    "deathYear": "",
    "bio": ""
  },
  "category": "",
  "lyrics": "Amazing Grace shall always be my\nsong of praise\nFor it was grace that brought me\nliberty\nI do not know just why He ever\ncame to love me so\nHe looked beyond my faults and\nsaw my need\n\nAnd I shall forever lift mine eyes to\nCalvary\nTo view the cross where Jesus died\nfor me\n\nHow marvelous the grace that\ncaught my falling soul\nHe looked beyond my faults and\nsaw my need\n\nI shall forever lift mine eyes to\nCalvary\nTo view the cross where Jesus died\nfor me\nHow marvelous the grace that\ncaught my falling soul\nHe looked beyond my faults and\nsaw my needs\nHe looked beyond my faults and\nsaw my needs"
}