{
  "hymnNumber": "s53",
  "title": "It Is The Hand Of God On The Wall,",
  "author": {
    "name": "",
    "birthYear": "",
    "deathYear": "",
    "bio": ""
  },
  "category": "Chorus",
  "lyrics": "It is the hand of God on the wall,\nIt is the hand of God on the wall,\nIt is the hand of God on the wall\nIt is the hand of God\nThat's writing on the wall,\nProdigal Sons and daughters\nCome home,\nProdigal Sons and daughters come home,\nProdigal Sons and daughters come home,\nIt is the hand of God\nThat's writing on the wall."
}